README.md
setup.cfg
setup.py
alley/__init__.py
alley/alley_cli.py
alley/migrations.py
alley.egg-info/PKG-INFO
alley.egg-info/SOURCES.txt
alley.egg-info/dependency_links.txt
alley.egg-info/entry_points.txt
alley.egg-info/requires.txt
alley.egg-info/top_level.txt