Metadata-Version: 1.2
Name: alley
Version: 0.0.2
Summary: Framework agnostic MongoEngine migrations.
Home-page: https://github.com/xperscore/alley
Author: WhoKnows, Inc.
Author-email: dev@whoknows.com
License: BSD
Platform: any
Classifier: Environment :: Web Environment
Classifier: Intended Audience :: Developers
Classifier: License :: OSI Approved :: BSD License
Classifier: Operating System :: OS Independent
Classifier: Programming Language :: Python
Classifier: Topic :: Internet :: WWW/HTTP :: Dynamic Content
Classifier: Topic :: Software Development :: Libraries :: Python Modules
Requires-Python: >=2.7
